basic_argparse.py
basic_argparse-1.1.dist-info/DESCRIPTION.rst
basic_argparse-1.1.dist-info/METADATA
basic_argparse-1.1.dist-info/pydist.json
basic_argparse-1.1.dist-info/RECORD
basic_argparse-1.1.dist-info/top_level.txt
basic_argparse-1.1.dist-info/WHEEL
