Metadata-Version: 2.0
Name: basic-argparse
Version: 1.1
Summary: A helper function for setting up an argparse parser.
Home-page: https://github.com/MatthewDarling/basic_argparse
Author: Matthew Darling
Author-email: matthewjdarling@gmail.com
License: http://opensource.org/licenses/MIT
Platform: UNKNOWN
Classifier: Development Status :: 5 - Production/Stable
Classifier: Intended Audience :: Science/Research
Classifier: License :: OSI Approved :: MIT License
Classifier: Natural Language :: English
Classifier: Operating System :: OS Independent
Classifier: Programming Language :: Python
Classifier: Programming Language :: Python :: 2
Classifier: Programming Language :: Python :: 3
Classifier: Topic :: Scientific/Engineering
